lqp/__init__.py
lqp/cli.py
lqp/emit.py
lqp/ir.py
lqp/parser.py
lqp/print.py
lqp/validator.py
lqp/proto/v1/fragments_pb2.py
lqp/proto/v1/fragments_pb2.pyi
lqp/proto/v1/logic_pb2.py
lqp/proto/v1/logic_pb2.pyi
lqp/proto/v1/transactions_pb2.py
lqp/proto/v1/transactions_pb2.pyi
meta/__init__.py
meta/cli.py
meta/gensym.py
meta/grammar.py
meta/grammar_gen.py
meta/grammar_gen_builtins.py
meta/grammar_gen_rewrites.py
meta/grammar_utils.py
meta/proto_ast.py
meta/proto_parser.py
meta/target.py
meta/target_utils.py
lqp-0.2.1.dist-info/METADATA
lqp-0.2.1.dist-info/WHEEL
lqp-0.2.1.dist-info/entry_points.txt
lqp-0.2.1.dist-info/top_level.txt
lqp-0.2.1.dist-info/RECORD
