Metadata-Version: 2.4
Name: lqp
Version: 0.2.1
Summary: Validate and translate Logical Query Protocol (LQP) S-expressions into Protobuf
Author-email: Niko Göbel <nikolas.goebel@relational.ai>, David Zhao <david.zhao@relational.ai>, Minsung Cho <minsung.cho@relational.ai>, Martin McGrane <martin.mcgrane@relational.ai>, Sławek Staworko <slawek.staworko@relational.ai>, Nate Nystrom <nate.nystrom@relational.ai>
Requires-Dist: lark>=1.1.9
Requires-Dist: protobuf<5.0.0,>=3.20.3
Requires-Dist: colorama
Requires-Dist: more-itertools
Provides-Extra: test
Requires-Dist: pytest>=7.0.0; extra == "test"
Requires-Dist: pytest-snapshot; extra == "test"
Requires-Dist: pyrefly==0.25.1; extra == "test"
